ccdev/__init__.py
ccdev/__main__.py
ccdev/command_factory.py
ccdev/command_line_app.py
ccdev/docopt_parser.py
devtask/__init__.py
devtask/extend_process.py
devtask/object_factory.py
devtask/repository.py
devtask/commands/__init__.py
devtask/commands/extend_process.py
devtask/test/__init__.py
devtask/test/test_extend_process.py
devtask/test/test_path.py
devtask/test/test_process_builder.py
devtask/test/test_repository.py
sql_gen/__init__.py
sql_gen/__main__.py
sql_gen/app_project.py
sql_gen/config.py
sql_gen/create_document_from_template_command.py
sql_gen/dtask_parser.py
sql_gen/exceptions.py
sql_gen/commands/__init__.py
sql_gen/commands/create_sql_cmd.py
sql_gen/commands/print_sql_cmd.py
sql_gen/commands/run_sql_cmd.py
sql_gen/commands/verify_templates_cmd.py
sql_gen/database/__init__.py
sql_gen/database/database.py
sql_gen/database/query_runner.py
sql_gen/database/sqlparser.py
sql_gen/database/sqltable.py
sql_gen/docugen/__init__.py
sql_gen/docugen/completer.py
sql_gen/docugen/env_builder.py
sql_gen/docugen/prompt.py
sql_gen/docugen/prompt_visitor.py
sql_gen/docugen/source_inspector.py
sql_gen/docugen/template_context.py
sql_gen/docugen/template_filler.py
sql_gen/docugen/template_inliner.py
sql_gen/emproject/__init__.py
sql_gen/emproject/ccadmin.py
sql_gen/emproject/em_project.py
sql_gen/emproject/emsvn.py
sql_gen/log/__init__.py
sql_gen/log/handlers.py
sql_gen/log/log.py
sql_gen/log/log2.py
sql_gen/log/logging.yaml
sql_gen/log/programatic_logger.py
sql_gen/log/handlers2/__init__.py
sql_gen/sqltask_jinja/__init__.py
sql_gen/sqltask_jinja/context.py
sql_gen/sqltask_jinja/globals.py
sql_gen/sqltask_jinja/sqltask_env.py
sql_gen/sqltask_jinja/filters/__init__.py
sql_gen/sqltask_jinja/filters/codepath.py
sql_gen/sqltask_jinja/filters/default.py
sql_gen/sqltask_jinja/filters/description.py
sql_gen/sqltask_jinja/filters/other.py
sql_gen/sqltask_jinja/filters/print.py
sql_gen/sqltask_jinja/filters/prompt_filter.py
sql_gen/sqltask_jinja/filters/suggest.py
em_sqltask-0.0.1a50.dist-info/LICENSE
em_sqltask-0.0.1a50.dist-info/METADATA
em_sqltask-0.0.1a50.dist-info/WHEEL
em_sqltask-0.0.1a50.dist-info/entry_points.txt
em_sqltask-0.0.1a50.dist-info/top_level.txt
em_sqltask-0.0.1a50.dist-info/RECORD
