Metadata-Version: 2.1
Name: em-sqltask
Version: 0.0.1a50
Summary: A helper to populate jinja templates
Home-page: https://bfs-eng-can05.kana-test.com/dgarcia/em_automation
Author: David Alvarez Garcia
Author-email: david.avgarcia@gmail.com
License: UNKNOWN
Platform: UNKNOWN
Classifier: Programming Language :: Python :: 3.6
Classifier: License :: OSI Approved :: MIT License
Classifier: Operating System :: OS Independent
Requires-Dist: Jinja2
Requires-Dist: pymssql
Requires-Dist: fuzzyfinder
Requires-Dist: prompt-toolkit
Requires-Dist: svn
Requires-Dist: pyperclip
Requires-Dist: PyYAML
Requires-Dist: cx-Oracle
Requires-Dist: prettytable
Requires-Dist: sqlparse
Requires-Dist: pytest
Requires-Dist: docopt
Requires-Dist: lxml
